ofxstatement_bancoposta-1.0.4-py3.11-nspkg.pth
ofxstatement/plugins/bancoposta.py
ofxstatement/plugins/bancopostaTransaction.py
ofxstatement/plugins/bancopostacsvparser.py
ofxstatement/plugins/bancopostapdfparser.py
ofxstatement_bancoposta-1.0.4.dist-info/METADATA
ofxstatement_bancoposta-1.0.4.dist-info/WHEEL
ofxstatement_bancoposta-1.0.4.dist-info/entry_points.txt
ofxstatement_bancoposta-1.0.4.dist-info/namespace_packages.txt
ofxstatement_bancoposta-1.0.4.dist-info/top_level.txt
ofxstatement_bancoposta-1.0.4.dist-info/zip-safe
ofxstatement_bancoposta-1.0.4.dist-info/RECORD
