Metadata-Version: 2.2
Name: ofxstatement-bancoposta
Version: 1.0.4
Summary: Bancoposta plugin for ofxstatement
Home-page: https://github.com/lorenzogiudici5/ofxstatement-bancoposta
Author: Lorenzo Giudici
Author-email: lorenzogiudici5@gmail.com
License: GPLv3
Keywords: ofx,banking,statement,bancoposta
Classifier: Development Status :: 5 - Production/Stable
Classifier: Programming Language :: Python :: 3
Classifier: Natural Language :: English
Classifier: Topic :: Office/Business :: Financial :: Accounting
Classifier: Topic :: Utilities
Classifier: Environment :: Console
Classifier: Operating System :: OS Independent
Classifier: License :: OSI Approved :: GNU General Public License v3 (GPLv3)
Requires-Dist: ofxstatement
Requires-Dist: pandas
Requires-Dist: tabula-py
Requires-Dist: pypdf2
Provides-Extra: test
Requires-Dist: pytest; extra == "test"
Dynamic: author
Dynamic: author-email
Dynamic: classifier
Dynamic: description
Dynamic: description-content-type
Dynamic: home-page
Dynamic: keywords
Dynamic: license
Dynamic: provides-extra
Dynamic: requires-dist
Dynamic: summary
